[{"alert_type":"anomaly_partner_leads_low","severity":"warning","title":"Careers360: low weekly leads","message":"Latest week 123 vs avg 1990 (-94%)","metric_value":123.0,"threshold":1990.2142857142858,"created_at":"2026-07-23T18:31:36.748355"},{"alert_type":"anomaly_partner_leads_low","severity":"warning","title":"College Dunia: low weekly leads","message":"Latest week 288 vs avg 6545 (-96%)","metric_value":288.0,"threshold":6545.210526315789,"created_at":"2026-07-23T18:31:36.748355"},{"alert_type":"anomaly_partner_leads_high","severity":"info","title":"College Hai: spike in weekly leads","message":"Latest week 5195 vs avg 1353 (+284%)","metric_value":5195.0,"threshold":1353.2380952380952,"created_at":"2026-07-23T18:31:36.748355"},{"alert_type":"anomaly_contactability","severity":"warning","title":"College Hai: contactability dip","message":"Weekly contactability 0.0% vs avg 18.6%","metric_value":0.019249278152069296,"threshold":18.61785937237411,"created_at":"2026-07-23T18:31:36.748355"},{"alert_type":"anomaly_partner_leads_low","severity":"warning","title":"College Wollege: low weekly leads","message":"Latest week 501 vs avg 1578 (-68%)","metric_value":501.0,"threshold":1578.4285714285713,"created_at":"2026-07-23T18:31:36.748355"},{"alert_type":"anomaly_contactability","severity":"warning","title":"College Wollege: contactability dip","message":"Weekly contactability 0.0% vs avg 18.1%","metric_value":0.0,"threshold":18.087598984279115,"created_at":"2026-07-23T18:31:36.748355"},{"alert_type":"anomaly_partner_leads_low","severity":"warning","title":"Kollege Apply: low weekly leads","message":"Latest week 6966 vs avg 23135 (-70%)","metric_value":6966.0,"threshold":23134.75,"created_at":"2026-07-23T18:31:36.748355"}]